iris_devtester/__init__.py
iris_devtester/cli/__init__.py
iris_devtester/cli/__main__.py
iris_devtester/cli/connection_commands.py
iris_devtester/cli/container.py
iris_devtester/cli/container_commands.py
iris_devtester/cli/fixture_commands.py
iris_devtester/config/__init__.py
iris_devtester/config/auto_discovery.py
iris_devtester/config/container_config.py
iris_devtester/config/container_state.py
iris_devtester/config/defaults.py
iris_devtester/config/discovery.py
iris_devtester/config/models.py
iris_devtester/config/presets.py
iris_devtester/config/yaml_loader.py
iris_devtester/connections/__init__.py
iris_devtester/connections/auto_discovery.py
iris_devtester/connections/connection.py
iris_devtester/connections/dbapi.py
iris_devtester/connections/jdbc.py
iris_devtester/connections/manager.py
iris_devtester/connections/models.py
iris_devtester/connections/retry.py
iris_devtester/containers/__init__.py
iris_devtester/containers/cpf_manager.py
iris_devtester/containers/iris_container.py
iris_devtester/containers/models.py
iris_devtester/containers/monitor_utils.py
iris_devtester/containers/monitoring.py
iris_devtester/containers/performance.py
iris_devtester/containers/validation.py
iris_devtester/containers/wait_strategies.py
iris_devtester/fixtures/__init__.py
iris_devtester/fixtures/creator.py
iris_devtester/fixtures/loader.py
iris_devtester/fixtures/manifest.py
iris_devtester/fixtures/obj_export.py
iris_devtester/fixtures/validator.py
iris_devtester/integrations/__init__.py
iris_devtester/integrations/langchain.py
iris_devtester/ports/__init__.py
iris_devtester/ports/assignment.py
iris_devtester/ports/exceptions.py
iris_devtester/ports/registry.py
iris_devtester/testing/__init__.py
iris_devtester/testing/fixtures.py
iris_devtester/testing/helpers.py
iris_devtester/testing/models.py
iris_devtester/testing/schema_reset.py
iris_devtester/utils/__init__.py
iris_devtester/utils/container_port.py
iris_devtester/utils/container_status.py
iris_devtester-1.10.0.dist-info/licenses/LICENSE
iris_devtester-1.10.0.dist-info/METADATA
iris_devtester-1.10.0.dist-info/WHEEL
iris_devtester-1.10.0.dist-info/entry_points.txt
iris_devtester-1.10.0.dist-info/top_level.txt
iris_devtester-1.10.0.dist-info/RECORD
