Metadata-Version: 2.4
Name: iris-devtester
Version: 1.10.0
Summary: Battle-tested InterSystems IRIS infrastructure utilities for Python development
Author-email: InterSystems Community <community@intersystems.com>
Maintainer-email: Thomas Dyar <thomas.dyar@intersystems.com>
Project-URL: Homepage, https://github.com/intersystems-community/iris-devtester
Project-URL: Documentation, https://github.com/intersystems-community/iris-devtester/blob/main/README.md
Project-URL: Repository, https://github.com/intersystems-community/iris-devtester
Project-URL: Issues, https://github.com/intersystems-community/iris-devtester/issues
Project-URL: Changelog, https://github.com/intersystems-community/iris-devtester/blob/main/CHANGELOG.md
Project-URL: Agent Skills, https://github.com/intersystems-community/iris-devtester/blob/main/SKILL.md
Project-URL: Getting Started, https://github.com/intersystems-community/iris-devtester/blob/main/docs/GETTING_STARTED.md
Project-URL: Troubleshooting, https://github.com/intersystems-community/iris-devtester/blob/main/docs/TROUBLESHOOTING.md
Keywords: intersystems,iris,database,testing,testcontainers,docker,devtools
Classifier: Development Status :: 5 - Production/Stable
Classifier: Intended Audience :: Developers
Classifier: Programming Language :: Python :: 3
Classifier: Programming Language :: Python :: 3.9
Classifier: Programming Language :: Python :: 3.10
Classifier: Programming Language :: Python :: 3.11
Classifier: Programming Language :: Python :: 3.12
Classifier: Topic :: Software Development :: Testing
Classifier: Topic :: Database
Classifier: Framework :: Pytest
Requires-Python: >=3.9
License-File: LICENSE
Requires-Dist: testcontainers>=4.0.0
Requires-Dist: testcontainers-iris>=1.2.2
Requires-Dist: python-dotenv>=1.0.0
Requires-Dist: docker>=6.0.0
Requires-Dist: filelock>=3.13.0
Requires-Dist: click>=8.0.0
Requires-Dist: PyYAML>=6.0
Requires-Dist: pydantic>=2.0.0
Provides-Extra: dbapi
Requires-Dist: intersystems-irispython>=3.2.0; extra == "dbapi"
Provides-Extra: jdbc
Requires-Dist: jaydebeapi>=1.2.3; extra == "jdbc"
Requires-Dist: JPype1>=1.4.0; extra == "jdbc"
Provides-Extra: all
Requires-Dist: intersystems-irispython>=3.2.0; extra == "all"
Requires-Dist: jaydebeapi>=1.2.3; extra == "all"
Requires-Dist: JPype1>=1.4.0; extra == "all"
Provides-Extra: test
Requires-Dist: pytest>=8.0.0; extra == "test"
Requires-Dist: pytest-cov>=5.0.0; extra == "test"
Requires-Dist: pytest-asyncio>=0.23.0; extra == "test"
Requires-Dist: pytest-timeout>=2.2.0; extra == "test"
Provides-Extra: dev
Requires-Dist: black>=24.0.0; extra == "dev"
Requires-Dist: isort>=5.13.0; extra == "dev"
Requires-Dist: mypy>=1.8.0; extra == "dev"
Requires-Dist: flake8>=7.0.0; extra == "dev"
Requires-Dist: pre-commit>=3.6.0; extra == "dev"
Requires-Dist: build>=1.0.0; extra == "dev"
Requires-Dist: twine>=5.0.0; extra == "dev"
Provides-Extra: docs
Requires-Dist: sphinx>=7.0.0; extra == "docs"
Requires-Dist: sphinx-rtd-theme>=2.0.0; extra == "docs"
Requires-Dist: myst-parser>=2.0.0; extra == "docs"
Dynamic: license-file
